tasd/__init__.py
tasd/constants.py
tasd/file.py
tasd/packet.py
tasd/utils.py
tasd/packets/__init__.py
tasd/packets/extra.py
tasd/packets/general.py
tasd/packets/genesis.py
tasd/packets/input.py
tasd/packets/nes.py
tasd/packets/snes.py
tasd-1.0.0.dist-info/licenses/LICENSE
tasd-1.0.0.dist-info/METADATA
tasd-1.0.0.dist-info/WHEEL
tasd-1.0.0.dist-info/top_level.txt
tasd-1.0.0.dist-info/RECORD
