Metadata-Version: 2.4
Name: tasd
Version: 1.0.0
Summary: TASD file serializer and deserializer
Author-email: TheMas3212 <mas3212@gmail.com>
License-Expression: MIT
Project-URL: Homepage, https://github.com/themas3212/tasd-py
Project-URL: Issues, https://github.com/themas3212/tasd-py/issues
Classifier: Programming Language :: Python :: 3
Classifier: Operating System :: OS Independent
Requires-Python: >=3.10
License-File: LICENSE
Dynamic: license-file
